pokeapi_lib/__init__.py
pokeapi_lib/cache.py
pokeapi_lib/client.py
pokeapi_lib/config_lib.py
pokeapi_lib/core.py
pokeapi_lib/exceptions.py
pokeapi_lib/models.py
pokeapi_wrapper_lib-0.1.0.dist-info/METADATA
pokeapi_wrapper_lib-0.1.0.dist-info/WHEEL
pokeapi_wrapper_lib-0.1.0.dist-info/top_level.txt
pokeapi_wrapper_lib-0.1.0.dist-info/RECORD
