Metadata-Version: 2.4
Name: pokeapi_wrapper_lib
Version: 0.1.0
Summary: An asynchronous Python wrapper library for PokeAPI v2 with caching and Pydantic models.
Author-email: Nick Miethe <miethe.dev@gmail.com>
License: MIT
Project-URL: Homepage, https://github.com/miethe/pokeapi_wrapper_lib
Classifier: Programming Language :: Python :: 3
Classifier: License :: OSI Approved :: MIT License
Classifier: Operating System :: OS Independent
Classifier: Intended Audience :: Developers
Classifier: Topic :: Software Development :: Libraries :: Python Modules
Classifier: Topic :: Internet
Requires-Python: >=3.8
Requires-Dist: httpx[http2]>=0.24
Requires-Dist: pydantic>=2.0
Requires-Dist: redis[hiredis]>=4.4
